{
  "events": [
    {
      "tick": 58907,
      "action": "volunteered at the shelter"
    },
    {
      "tick": 58967,
      "action": "stood up for a friend in an argument"
    },
    {
      "tick": 59027,
      "action": "volunteered at the shelter"
    },
    {
      "tick": 59087,
      "action": "slept through most of the day"
    },
    {
      "tick": 59117,
      "action": "volunteered at the shelter"
    },
    {
      "tick": 59177,
      "action": "stood up for a friend in an argument"
    },
    {
      "tick": 59207,
      "action": "volunteered at the shelter"
    },
    {
      "tick": 59237,
      "action": "slept through most of the day"
    },
    {
      "tick": 59297,
      "action": "stood up for a friend in an argument"
    },
    {
      "tick": 59327,
      "action": "volunteered at the shelter"
    },
    {
      "tick": 59357,
      "action": "volunteered at the shelter"
    },
    {
      "tick": 59387,
      "action": "slept through most of the day"
    },
    {
      "tick": 59477,
      "action": "stood up for a friend in an argument"
    },
    {
      "tick": 59717,
      "action": "slept through most of the day"
    },
    {
      "time": "2025-06-17 14:58",
      "summary": "Phoenix comforted Silas during a tough moment."
    },
    {
      "tick": 59747,
      "action": "slept through most of the day"
    },
    {
      "tick": 60017,
      "action": "slept through most of the day"
    },
    {
      "tick": 60437,
      "action": "stood up for a friend in an argument"
    },
    {
      "tick": 60497,
      "action": "slept through most of the day"
    },
    {
      "time": "2025-06-17 19:09",
      "summary": "Phoenix stood up for Alex in an argument."
    },
    {
      "tick": 60617,
      "action": "slept through most of the day"
    },
    {
      "tick": 60707,
      "action": "volunteered at the shelter"
    },
    {
      "tick": 60887,
      "action": "stood up for a friend in an argument"
    },
    {
      "tick": 61007,
      "action": "volunteered at the shelter"
    },
    {
      "time": "2025-06-17 20:21",
      "summary": "Phoenix challenged Sol to improve themselves."
    },
    {
      "tick": 61337,
      "action": "slept through most of the day"
    },
    {
      "time": "2025-06-17 20:27",
      "summary": "Phoenix ignored Zara completely."
    },
    {
      "tick": 61367,
      "action": "volunteered at the shelter"
    },
    {
      "tick": 61397,
      "action": "slept through most of the day"
    },
    {
      "tick": 61518,
      "action": "stood up for a friend in an argument"
    },
    {
      "tick": 61549,
      "action": "volunteered at the shelter"
    },
    {
      "tick": 61580,
      "action": "slept through most of the day"
    },
    {
      "tick": 61610,
      "action": "slept through most of the day"
    },
    {
      "time": "2025-06-17 20:49",
      "summary": "Isla chatted with Phoenix about the weather."
    },
    {
      "tick": 61641,
      "action": "volunteered at the shelter"
    },
    {
      "time": "2025-06-17 20:49",
      "summary": "Phoenix chatted with Indigo about the weather."
    },
    {
      "tick": 61672,
      "action": "slept through most of the day"
    },
    {
      "tick": 61733,
      "action": "slept through most of the day"
    },
    {
      "time": "2025-06-17 20:51",
      "summary": "Max chatted with Phoenix about the weather."
    },
    {
      "tick": 61764,
      "action": "volunteered at the shelter"
    },
    {
      "tick": 61795,
      "action": "stood up for a friend in an argument"
    },
    {
      "tick": 61826,
      "action": "stood up for a friend in an argument"
    },
    {
      "time": "2025-06-17 20:51",
      "summary": "Sage gave advice to Phoenix after a breakup."
    },
    {
      "tick": 61857,
      "action": "slept through most of the day"
    },
    {
      "tick": 61887,
      "action": "volunteered at the shelter"
    },
    {
      "tick": 62008,
      "action": "volunteered at the shelter"
    },
    {
      "tick": 62039,
      "action": "stood up for a friend in an argument"
    },
    {
      "tick": 62070,
      "action": "slept through most of the day"
    },
    {
      "tick": 62101,
      "action": "volunteered at the shelter"
    },
    {
      "tick": 62132,
      "action": "slept through most of the day"
    },
    {
      "tick": 62163,
      "action": "stood up for a friend in an argument"
    },
    {
      "time": "2025-06-17 20:56",
      "summary": "Phoenix challenged Elio to improve themselves."
    },
    {
      "tick": 62194,
      "action": "volunteered at the shelter"
    },
    {
      "tick": 62255,
      "action": "stood up for a friend in an argument"
    },
    {
      "time": "2025-06-17 20:56",
      "summary": "Indigo challenged Phoenix to improve themselves."
    },
    {
      "tick": 62286,
      "action": "volunteered at the shelter"
    },
    {
      "time": "2025-06-17 20:56",
      "summary": "Phoenix chatted with Dax about the weather."
    },
    {
      "tick": 62317,
      "action": "slept through most of the day"
    },
    {
      "time": "2025-06-17 20:56",
      "summary": "Phoenix chatted with Nyx about the weather."
    },
    {
      "tick": 62348,
      "action": "slept through most of the day"
    },
    {
      "tick": 62379,
      "action": "stood up for a friend in an argument"
    },
    {
      "tick": 62410,
      "action": "volunteered at the shelter"
    },
    {
      "tick": 62441,
      "action": "stood up for a friend in an argument"
    },
    {
      "tick": 62471,
      "action": "stood up for a friend in an argument"
    },
    {
      "tick": 62531,
      "action": "slept through most of the day"
    },
    {
      "time": "2025-06-17 23:36",
      "summary": "Taylor ignored Phoenix completely."
    },
    {
      "tick": 62592,
      "action": "volunteered at the shelter"
    },
    {
      "tick": 62622,
      "action": "volunteered at the shelter"
    },
    {
      "time": "2025-06-18 00:17",
      "summary": "Phoenix chatted with Zara about the weather."
    },
    {
      "tick": 62832,
      "action": "stood up for a friend in an argument"
    },
    {
      "tick": 62892,
      "action": "slept through most of the day"
    },
    {
      "tick": 62982,
      "action": "stood up for a friend in an argument"
    },
    {
      "tick": 63042,
      "action": "volunteered at the shelter"
    },
    {
      "tick": 63073,
      "action": "volunteered at the shelter"
    },
    {
      "tick": 63104,
      "action": "stood up for a friend in an argument"
    },
    {
      "time": "2025-06-18 02:49",
      "summary": "Milo chatted with Phoenix about the weather."
    },
    {
      "tick": 63135,
      "action": "volunteered at the shelter"
    },
    {
      "tick": 63166,
      "action": "volunteered at the shelter"
    },
    {
      "tick": 63197,
      "action": "stood up for a friend in an argument"
    },
    {
      "time": "2025-06-18 02:51",
      "summary": "Dax comforted Phoenix during a tough moment."
    },
    {
      "tick": 63227,
      "action": "slept through most of the day"
    },
    {
      "tick": 63317,
      "action": "volunteered at the shelter"
    },
    {
      "tick": 63347,
      "action": "slept through most of the day"
    },
    {
      "tick": 63377,
      "action": "stood up for a friend in an argument"
    },
    {
      "tick": 63437,
      "action": "helped an elderly neighbor",
      "timestamp": "2025-06-18 14:00:10"
    },
    {
      "tick": 63947,
      "action": "organized a community event",
      "timestamp": "2025-06-19 10:23:28"
    },
    {
      "tick": 63977,
      "action": "organized a community event",
      "timestamp": "2025-06-19 10:52:43"
    },
    {
      "tick": 64037,
      "action": "organized a community event",
      "timestamp": "2025-06-19 10:53:20"
    },
    {
      "tick": 64067,
      "action": "volunteered at local shelter",
      "timestamp": "2025-06-19 10:53:22"
    },
    {
      "tick": 64097,
      "action": "helped an elderly neighbor",
      "timestamp": "2025-06-19 10:53:24"
    },
    {
      "tick": 64127,
      "action": "helped an elderly neighbor",
      "timestamp": "2025-06-19 10:53:26"
    },
    {
      "tick": 64157,
      "action": "stood up for someone",
      "timestamp": "2025-06-19 10:54:00"
    },
    {
      "tick": 64187,
      "action": "stood up for someone",
      "timestamp": "2025-06-19 10:54:11"
    },
    {
      "tick": 64217,
      "action": "organized a community event",
      "timestamp": "2025-06-19 11:07:34"
    },
    {
      "tick": 64247,
      "action": "helped an elderly neighbor",
      "timestamp": "2025-06-19 11:07:53"
    },
    {
      "tick": 64277,
      "action": "organized a community event",
      "timestamp": "2025-06-19 11:08:03"
    },
    {
      "tick": 64307,
      "action": "stood up for someone",
      "timestamp": "2025-06-19 11:58:12"
    },
    {
      "tick": 64367,
      "action": "volunteered at local shelter",
      "timestamp": "2025-06-19 11:59:44"
    },
    {
      "tick": 64397,
      "action": "volunteered at local shelter",
      "timestamp": "2025-06-19 11:59:53"
    },
    {
      "tick": 64457,
      "action": "organized a community event",
      "timestamp": "2025-06-19 12:00:00"
    },
    {
      "tick": 64517,
      "action": "stood up for someone",
      "timestamp": "2025-06-19 12:02:29"
    },
    {
      "tick": 64577,
      "action": "organized a community event",
      "timestamp": "2025-06-19 12:03:13"
    },
    {
      "tick": 64607,
      "action": "stood up for someone",
      "timestamp": "2025-06-19 12:05:46"
    },
    {
      "tick": 64667,
      "action": "helped an elderly neighbor",
      "timestamp": "2025-06-19 12:06:00"
    },
    {
      "tick": 64727,
      "action": "volunteered at local shelter",
      "timestamp": "2025-06-19 12:06:38"
    },
    {
      "tick": 64757,
      "action": "helped an elderly neighbor",
      "timestamp": "2025-06-19 12:06:59"
    },
    {
      "tick": 64787,
      "action": "stood up for someone",
      "timestamp": "2025-06-19 12:07:27"
    },
    {
      "tick": 64817,
      "action": "organized a community event",
      "timestamp": "2025-06-19 12:10:29"
    },
    {
      "tick": 64847,
      "action": "volunteered at local shelter",
      "timestamp": "2025-06-19 12:10:35"
    },
    {
      "tick": 64877,
      "action": "organized a community event",
      "timestamp": "2025-06-19 12:10:39"
    },
    {
      "tick": 64907,
      "action": "organized a community event",
      "timestamp": "2025-06-19 12:10:42"
    },
    {
      "tick": 64937,
      "action": "volunteered at local shelter",
      "timestamp": "2025-06-19 12:11:02"
    },
    {
      "tick": 64967,
      "action": "volunteered at local shelter",
      "timestamp": "2025-06-19 12:39:12"
    },
    {
      "tick": 64997,
      "action": "volunteered at local shelter",
      "timestamp": "2025-06-19 12:41:09"
    },
    {
      "tick": 65027,
      "action": "stood up for someone",
      "timestamp": "2025-06-19 12:42:57"
    },
    {
      "tick": 65087,
      "action": "stood up for someone",
      "timestamp": "2025-06-19 12:45:14"
    },
    {
      "tick": 65117,
      "action": "stood up for someone",
      "timestamp": "2025-06-19 12:46:18"
    },
    {
      "tick": 65147,
      "action": "stood up for someone",
      "timestamp": "2025-06-19 12:49:25"
    },
    {
      "tick": 65177,
      "action": "organized a community event",
      "timestamp": "2025-06-19 12:49:26"
    },
    {
      "tick": 65207,
      "action": "helped an elderly neighbor",
      "timestamp": "2025-06-19 12:49:28"
    },
    {
      "tick": 65237,
      "action": "helped an elderly neighbor",
      "timestamp": "2025-06-19 12:56:09"
    },
    {
      "tick": 65267,
      "action": "volunteered at local shelter",
      "timestamp": "2025-06-19 13:59:40"
    },
    {
      "tick": 65297,
      "action": "stood up for someone",
      "timestamp": "2025-06-19 14:09:24"
    },
    {
      "tick": 65327,
      "action": "organized a community event",
      "timestamp": "2025-06-19 15:19:58"
    },
    {
      "tick": 65357,
      "action": "volunteered at local shelter",
      "timestamp": "2025-06-19 15:22:53"
    },
    {
      "tick": 65387,
      "action": "volunteered at local shelter",
      "timestamp": "2025-06-19 15:25:13"
    },
    {
      "tick": 65417,
      "action": "helped an elderly neighbor",
      "timestamp": "2025-06-19 15:25:15"
    },
    {
      "tick": 65447,
      "action": "stood up for someone",
      "timestamp": "2025-06-19 15:25:46"
    },
    {
      "tick": 65477,
      "action": "organized a community event",
      "timestamp": "2025-06-19 15:27:42"
    },
    {
      "tick": 65507,
      "action": "volunteered at local shelter",
      "timestamp": "2025-06-20 10:46:26"
    },
    {
      "tick": 65537,
      "action": "volunteered at local shelter",
      "timestamp": "2025-06-20 14:14:43"
    },
    {
      "tick": 65567,
      "action": "organized a community event",
      "timestamp": "2025-06-20 14:22:18"
    },
    {
      "tick": 65597,
      "action": "organized a community event",
      "timestamp": "2025-06-20 14:22:53"
    },
    {
      "tick": 65627,
      "action": "helped an elderly neighbor",
      "timestamp": "2025-06-20 14:24:10"
    },
    {
      "tick": 65657,
      "action": "helped an elderly neighbor",
      "timestamp": "2025-06-20 14:25:15"
    },
    {
      "tick": 65687,
      "action": "volunteered at local shelter",
      "timestamp": "2025-06-22 00:18:14"
    },
    {
      "tick": 65717,
      "action": "volunteered at local shelter",
      "timestamp": "2025-06-22 00:18:34"
    },
    {
      "tick": 65747,
      "action": "organized a community event",
      "timestamp": "2025-06-22 00:18:35"
    },
    {
      "tick": 65777,
      "action": "volunteered at local shelter",
      "timestamp": "2025-06-22 00:27:36"
    },
    {
      "tick": 65807,
      "action": "organized a community event",
      "timestamp": "2025-06-22 00:27:47"
    },
    {
      "tick": 65837,
      "action": "helped an elderly neighbor",
      "timestamp": "2025-06-22 00:37:38"
    },
    {
      "tick": 65867,
      "action": "helped an elderly neighbor",
      "timestamp": "2025-06-22 00:37:39"
    },
    {
      "tick": 65897,
      "action": "organized a community event",
      "timestamp": "2025-06-22 00:37:42"
    },
    {
      "tick": 65927,
      "action": "helped an elderly neighbor",
      "timestamp": "2025-06-22 00:38:43"
    },
    {
      "tick": 65957,
      "action": "organized a community event",
      "timestamp": "2025-06-22 00:39:41"
    },
    {
      "tick": 65987,
      "action": "stood up for someone",
      "timestamp": "2025-06-22 00:39:42"
    },
    {
      "tick": 66017,
      "action": "organized a community event",
      "timestamp": "2025-06-22 00:39:44"
    },
    {
      "tick": 66047,
      "action": "organized a community event",
      "timestamp": "2025-06-22 00:39:46"
    },
    {
      "tick": 66077,
      "action": "helped an elderly neighbor",
      "timestamp": "2025-06-22 00:40:22"
    },
    {
      "tick": 66107,
      "action": "volunteered at local shelter",
      "timestamp": "2025-06-22 00:44:05"
    },
    {
      "tick": 66137,
      "action": "stood up for someone",
      "timestamp": "2025-06-22 00:45:58"
    }
  ]
}